{
  "commits": [
    {
      "id": "452687e810069d8803c6e75fb92de7d87eda3699",
      "who": "Sam Brannen <sam@sambrannen.com>",
      "when": "2016-01-02T22:24:05+01:00",
      "all": 146,
      "test": 9,
      "testable": 146,
      "pct": 6.2
    },
    {
      "id": "eb4d6401bb646f5c77b89149aeb6648f0b3ab478",
      "who": "Sam Brannen <sam@sambrannen.com>",
      "when": "2016-01-02T22:22:16+01:00",
      "all": 17,
      "test": 0,
      "testable": 17,
      "pct": 0.0
    },
    {
      "id": "53a72fef0887a83857b1e80e4a8da44c6d170ca1",
      "who": "Marc Philipp <mail@marcphilipp.de>",
      "when": "2016-01-02T22:21:25+01:00",
      "all": 41,
      "test": 41,
      "testable": 41,
      "pct": 100.0
    },
    {
      "id": "2309f89018bcf0b812f7e893f1f4d8a6c0517fee",
      "who": "Marc Philipp <mail@marcphilipp.de>",
      "when": "2016-01-02T21:56:36+01:00",
      "all": 199,
      "test": 55,
      "testable": 199,
      "pct": 27.6
    },
    {
      "id": "266b9b90ab55ed3ffdfd43960309606300db8758",
      "who": "Sam Brannen <sam@sambrannen.com>",
      "when": "2016-01-02T19:50:20+01:00",
      "all": 97,
      "test": 44,
      "testable": 97,
      "pct": 45.4
    },
    {
      "id": "5a93555401ce7ad317c872534d9494d61d1da605",
      "who": "Sam Brannen <sam@sambrannen.com>",
      "when": "2016-01-02T19:35:54+01:00",
      "all": 45,
      "test": 0,
      "testable": 45,
      "pct": 0.0
    },
    {
      "id": "a30a5aacaac31885206569b1655f8c8ce68cf5ef",
      "who": "Sam Brannen <sam@sambrannen.com>",
      "when": "2016-01-02T19:18:52+01:00",
      "all": 86,
      "test": 0,
      "testable": 86,
      "pct": 0.0
    },
    {
      "id": "fce8527e22cbe1e4bfa8da4b5b0fd4103ef024a4",
      "who": "Sam Brannen <sam@sambrannen.com>",
      "when": "2016-01-02T19:14:07+01:00",
      "all": 32,
      "test": 0,
      "testable": 32,
      "pct": 0.0
    },
    {
      "id": "90c7b161c547f033d10f8c5ae9293923addf6a5e",
      "who": "Sam Brannen <sam@sambrannen.com>",
      "when": "2016-01-02T19:13:39+01:00",
      "all": 29,
      "test": 0,
      "testable": 29,
      "pct": 0.0
    },
    {
      "id": "313993c9fabcc0bcb72b3f3e752b7e5fb81bac1a",
      "who": "Marc Philipp <mail@marcphilipp.de>",
      "when": "2016-01-02T19:24:14+01:00",
      "all": 67,
      "test": 44,
      "testable": 67,
      "pct": 65.7
    },
    {
      "id": "0e23f69b7d8a80684b087716738e4aa06bcdcbb2",
      "who": "Marc Philipp <mail@marcphilipp.de>",
      "when": "2016-01-02T18:59:43+01:00",
      "all": 13,
      "test": 0,
      "testable": 13,
      "pct": 0.0
    },
    {
      "id": "a1eb11673e2b7e69bc0c4c2f5c5b81cf572dfeab",
      "who": "Sam Brannen <sam@sambrannen.com>",
      "when": "2016-01-02T18:23:12+01:00",
      "all": 187,
      "test": 0,
      "testable": 187,
      "pct": 0.0
    },
    {
      "id": "355d64b574c534f35b4faeae1339b458a0787579",
      "who": "Sam Brannen <sam@sambrannen.com>",
      "when": "2016-01-02T18:06:27+01:00",
      "all": 40,
      "test": 0,
      "testable": 40,
      "pct": 0.0
    },
    {
      "id": "2a3c1b6ff5b4081e7eb30a5719568b6ce8cda0a5",
      "who": "Sam Brannen <sam@sambrannen.com>",
      "when": "2016-01-02T18:05:08+01:00",
      "all": 90,
      "test": 0,
      "testable": 90,
      "pct": 0.0
    },
    {
      "id": "2df8323212662afef2d1caa3c70bd5d0fda32223",
      "who": "Marc Philipp <mail@marcphilipp.de>",
      "when": "2016-01-02T17:28:37+01:00",
      "all": 224,
      "test": 142,
      "testable": 224,
      "pct": 63.4
    },
    {
      "id": "5df9d780fe448c38dbebf9c6406a3d9080880c8f",
      "who": "Sam Brannen <sam@sambrannen.com>",
      "when": "2016-01-02T00:50:41+01:00",
      "all": 30,
      "test": 30,
      "testable": 30,
      "pct": 100.0
    },
    {
      "id": "6237ee4b761b840f65e3c9363b9128f2bcd36913",
      "who": "Sam Brannen <sam@sambrannen.com>",
      "when": "2016-01-02T00:46:32+01:00",
      "all": 12,
      "test": 2,
      "testable": 12,
      "pct": 16.7
    }
  ],
  "description": "JUnit 5 (master branch)",
  "baseURL": "https://github.com/junit-team/junit5/commit/"
}