{
  "commits": [
    {
      "id": "3289d9422b535666786aa3201ea0f31ad5e1f7e3",
      "who": "kcooney@google.com",
      "when": "2015-05-26T21:07:51-07:00",
      "all": 42,
      "test": 0,
      "testable": 42,
      "pct": 0.0
    },
    {
      "id": "99da5691c6cf70af52c4793ffab717a9f3085753",
      "who": "me@shadowfacts.net",
      "when": "2015-05-31T13:34:37-04:00",
      "all": 3,
      "test": 0,
      "testable": 3,
      "pct": 0.0
    },
    {
      "id": "82118e728701b7b0f81a2dd4a69b2290de056b28",
      "who": "charlie@yandex-team.ru",
      "when": "2015-05-12T18:39:55+03:00",
      "all": 148,
      "test": 0,
      "testable": 148,
      "pct": 0.0
    },
    {
      "id": "03eff4b98a38d617a3d0cbc047221d7d337eeb86",
      "who": "EarthCitizen@users.noreply.github.com",
      "when": "2015-05-13T15:23:48-07:00",
      "all": 17,
      "test": 0,
      "testable": 17,
      "pct": 0.0
    }
  ],
  "description": "JUnit 4 (master branch)",
  "baseURL": "https://github.com/junit-team/junit4/commit/"
}