{
  "commits": [
    {
      "id": "a7fe983be2b03f75a7e310a996e719bc7d8a34cf",
      "who": "vsavkin <avix1000@gmail.com>",
      "when": "2016-03-15T15:01:08-07:00",
      "all": 9,
      "test": 0,
      "testable": 9,
      "pct": 0.0
    },
    {
      "id": "e1f8e54e34f49a1bedd10e4f0f01d00efdec20ce",
      "who": "vsavkin <avix1000@gmail.com>",
      "when": "2016-03-15T15:00:51-07:00",
      "all": 52,
      "test": 36,
      "testable": 49,
      "pct": 73.5
    }
  ],
  "description": "Angular (master branch)",
  "baseURL": "https://github.com/angular/angular/commit/"
}