{
  "commits": [
    {
      "id": "0f1d64ca577c8594e26b9e1663e49c8e1bc13757",
      "who": "antirez@gmail.com",
      "when": "2011-04-30T22:29:21+02:00",
      "all": 84,
      "test": 0,
      "testable": 84,
      "pct": 0.0
    },
    {
      "id": "7585836e6eb1c0199e8d9ea2c3f7a0f67b03c00b",
      "who": "antirez@gmail.com",
      "when": "2011-04-30T17:46:52+02:00",
      "all": 118,
      "test": 0,
      "testable": 114,
      "pct": 0.0
    },
    {
      "id": "21d3294c7013a4385aebd84436394bb58e273093",
      "who": "antirez@gmail.com",
      "when": "2011-04-30T16:15:30+02:00",
      "all": 28567,
      "test": 0,
      "testable": 17144,
      "pct": 0.0
    }
  ],
  "description": "Redis (unstable branch)",
  "baseURL": "https://github.com/antirez/redis/commit/"
}