{
  "commits": [
    {
      "id": "7ec1f3e3c5d234f62c9ff22bb7a78c1a3b3e1372",
      "who": "mikedoerfler@users.sourceforge.net",
      "when": "2004-07-31T19:19:10+00:00",
      "all": 279,
      "test": 279,
      "testable": 279,
      "pct": 100.0
    },
    {
      "id": "bef591c84231802e778ace30c1c058000fcfd09e",
      "who": "mikedoerfler@users.sourceforge.net",
      "when": "2004-07-31T19:17:40+00:00",
      "all": 18,
      "test": 0,
      "testable": 18,
      "pct": 0.0
    },
    {
      "id": "bedf865394202c1a5b658a9faafa6d274401fd16",
      "who": "mikedoerfler@users.sourceforge.net",
      "when": "2004-07-31T19:16:44+00:00",
      "all": 30,
      "test": 0,
      "testable": 30,
      "pct": 0.0
    },
    {
      "id": "eaa03fb67b593b16b7dbe0cd632670f1ce062bb2",
      "who": "mikedoerfler@users.sourceforge.net",
      "when": "2004-07-31T14:51:01+00:00",
      "all": 388,
      "test": 388,
      "testable": 388,
      "pct": 100.0
    },
    {
      "id": "cf387eff40e5f7a49dd3bab7ef200c28104d4be1",
      "who": "mikedoerfler@users.sourceforge.net",
      "when": "2004-07-31T14:50:32+00:00",
      "all": 78,
      "test": 0,
      "testable": 78,
      "pct": 0.0
    },
    {
      "id": "dfab6e1fabb45e8473e753d54f6aa6ada41afbe5",
      "who": "mikedoerfler@users.sourceforge.net",
      "when": "2004-07-31T14:49:48+00:00",
      "all": 33,
      "test": 0,
      "testable": 33,
      "pct": 0.0
    }
  ],
  "description": "NHibernate (master branch)",
  "baseURL": "https://github.com/nhibernate/nhibernate-core/commit/"
}