{
  "commits": [
    {
      "id": "108fa1579247a92c8d6105aff5d2ea6b92129cb4",
      "who": "kalpakas.g@gmail.com",
      "when": "2018-01-15T16:10:55+02:00",
      "all": 312,
      "test": 0,
      "testable": 312,
      "pct": 0.0
    },
    {
      "id": "d6ba9f9fb42249746faca93223a8eb09de89c325",
      "who": "pete@bacondarwin.com",
      "when": "2018-01-15T16:10:32+00:00",
      "all": 30,
      "test": 0,
      "testable": 21,
      "pct": 0.0
    }
  ],
  "description": "Angular (master branch)",
  "baseURL": "https://github.com/angular/angular/commit/"
}