{
  "commits": [
    {
      "all": 16, 
      "who": "github@m3p.co.uk", 
      "when": "2014-12-18T13:37:21+00:00", 
      "pct": 0.0, 
      "test": 0, 
      "testable": 16, 
      "id": "0aa3d08bcd4e6c4bee00d8caf6484a0c39e649f3"
    }, 
    {
      "all": 149, 
      "who": "github@m3p.co.uk", 
      "when": "2014-12-18T12:56:26+00:00", 
      "pct": 22.0, 
      "test": 28, 
      "testable": 122, 
      "id": "fbfedbea89da8a196c6f9fc7dcd78128ff62571d"
    }, 
    {
      "all": 678, 
      "who": "github@m3p.co.uk", 
      "when": "2014-12-18T12:55:03+00:00", 
      "pct": 34.0, 
      "test": 209, 
      "testable": 602, 
      "id": "d1ce3487531ce12edfc6a5e554324b5603d0611a"
    }, 
    {
      "all": 2237, 
      "who": "github@m3p.co.uk", 
      "when": "2014-12-18T11:35:45+00:00", 
      "pct": 45.0, 
      "test": 952, 
      "testable": 2081, 
      "id": "f429432f974377b6d9496193e1a1b7e118255c3e"
    }, 
    {
      "all": 1614, 
      "who": "github@m3p.co.uk", 
      "when": "2014-12-18T11:19:25+00:00", 
      "pct": 0.0, 
      "test": 0, 
      "testable": 1614, 
      "id": "99bc9421a719782c6357f991c891af48d6e9de4a"
    }
  ], 
  "description": "Hamcrest Java (master branch)", 
  "baseURL": "https://github.com/hamcrest/JavaHamcrest/commit/"
}