{
  "commits": [
    {
      "id": "45e9f709ff22071e95fba998394ff8fd82b08a70",
      "who": "mikedoerfler@users.sourceforge.net",
      "when": "2004-11-27T01:03:39+00:00",
      "all": 33,
      "test": 0,
      "testable": 33,
      "pct": 0.0
    },
    {
      "id": "782e4188b3c18e96d68d1a2614eba8ddccf2646e",
      "who": "mikedoerfler@users.sourceforge.net",
      "when": "2004-11-27T01:00:09+00:00",
      "all": 14,
      "test": 0,
      "testable": 14,
      "pct": 0.0
    }
  ],
  "description": "NHibernate (master branch)",
  "baseURL": "https://github.com/nhibernate/nhibernate-core/commit/"
}