{
  "commits": [
    {
      "all": 26, 
      "who": "james.mudd@gmail.com", 
      "when": "2019-04-17T22:04:22+01:00", 
      "pct": 53.0, 
      "test": 14, 
      "testable": 26, 
      "id": "67bcac86e421eb07fff89a340ccd552052645d66"
    }, 
    {
      "all": 45, 
      "who": "phoenix384@gmx.de", 
      "when": "2019-04-24T20:39:35+02:00", 
      "pct": 0.0, 
      "test": 0, 
      "testable": 45, 
      "id": "5f54700d857619358c6467dc0e41e8d96ab4c235"
    }
  ], 
  "description": "Hamcrest Java (master branch)", 
  "baseURL": "https://github.com/hamcrest/JavaHamcrest/commit/"
}