{
  "commits": [
    {
      "id": "f9bababaa77726969e829950d246bc8618877372",
      "who": "matolson@amazon.com",
      "when": "2019-02-13T21:03:31+00:00",
      "all": 20,
      "test": 0,
      "testable": 20,
      "pct": 0.0
    },
    {
      "id": "fd7484cde2d9eb1f659232934ffef46da192b3a0",
      "who": "antirez@gmail.com",
      "when": "2019-02-13T18:59:59+01:00",
      "all": 54,
      "test": 0,
      "testable": 54,
      "pct": 0.0
    },
    {
      "id": "e819c2ef5b6f6b7c196cc7c00c543c4af8c703a7",
      "who": "antirez@gmail.com",
      "when": "2019-02-13T16:30:44+01:00",
      "all": 10,
      "test": 0,
      "testable": 10,
      "pct": 0.0
    },
    {
      "id": "a65094dae811770c904f9ec5bb54c41caf5d9f66",
      "who": "zhaozhao.zz@alibaba-inc.com",
      "when": "2019-02-13T11:47:10+08:00",
      "all": 10,
      "test": 0,
      "testable": 10,
      "pct": 0.0
    }
  ],
  "description": "Redis (unstable branch)",
  "baseURL": "https://github.com/antirez/redis/commit/"
}