{
  "commits": [
    {
      "id": "292dd7d905a4c3400f6411658c9ea24557b344d3",
      "who": "joerg.schaible@gmx.de",
      "when": "2012-11-30T10:19:03+00:00",
      "all": 12,
      "test": 0,
      "testable": 12,
      "pct": 0.0
    },
    {
      "id": "2a8689a0aa2f0fb3fd8bbd77b938693d390dfbdd",
      "who": "joerg.schaible@gmx.de",
      "when": "2012-11-30T08:35:19+00:00",
      "all": 17,
      "test": 0,
      "testable": 17,
      "pct": 0.0
    },
    {
      "id": "c3982eab0c0837b2fe1a33382083079ee3a0deee",
      "who": "joerg.schaible@gmx.de",
      "when": "2012-11-29T18:16:11+00:00",
      "all": 44,
      "test": 0,
      "testable": 34,
      "pct": 0.0
    },
    {
      "id": "162dfec72122da3d0ba720a4a4f4d2c74da5a88c",
      "who": "joerg.schaible@gmx.de",
      "when": "2012-11-14T12:50:47+00:00",
      "all": 26,
      "test": 26,
      "testable": 26,
      "pct": 100.0
    },
    {
      "id": "66bde074e0e35e3d61993b008c6e3779faba57ea",
      "who": "joerg.schaible@gmx.de",
      "when": "2012-11-01T17:07:16+00:00",
      "all": 9,
      "test": 0,
      "testable": 9,
      "pct": 0.0
    }
  ],
  "description": "XStream (master branch)",
  "baseURL": "https://github.com/x-stream/xstream/commit/"
}