{
  "commits": [
    {
      "id": "957f594d7cb596e495d166db3d3ecb5103abd7ea",
      "who": "kalpakas.g@gmail.com",
      "when": "2018-11-07T22:46:22+02:00",
      "all": 161,
      "test": 161,
      "testable": 161,
      "pct": 100.0
    },
    {
      "id": "8f120aff33c3644b82f4d2e2787c4c7ef9faac51",
      "who": "kalpakas.g@gmail.com",
      "when": "2018-11-07T22:45:40+02:00",
      "all": 100,
      "test": 0,
      "testable": 87,
      "pct": 0.0
    },
    {
      "id": "b0c75611d6ff193afd29cd12152c1b3e3f04424a",
      "who": "cedric@ninja-squad.com",
      "when": "2018-11-07T20:38:07+01:00",
      "all": 39,
      "test": 0,
      "testable": 39,
      "pct": 0.0
    },
    {
      "id": "e618032d53314545ba38b038da91d7fef2879765",
      "who": "matias@yearofmoo.com",
      "when": "2018-11-07T13:03:11-08:00",
      "all": 19,
      "test": 10,
      "testable": 19,
      "pct": 52.6
    }
  ],
  "description": "Angular (master branch)",
  "baseURL": "https://github.com/angular/angular/commit/"
}