{
  "commits": [
    {
      "id": "077d4657cce12a38d4f34266fc62c190b28235a9",
      "who": "saff@new-host-3.home",
      "when": "2009-06-04T12:52:28+08:00",
      "all": 169,
      "test": 66,
      "testable": 135,
      "pct": 48.9
    },
    {
      "id": "11258fcfd07dd63754fbea374bbba59ea82bc685",
      "who": "saff@new-host-3.home",
      "when": "2009-06-04T00:52:28-04:00",
      "all": 169,
      "test": 66,
      "testable": 135,
      "pct": 48.9
    },
    {
      "id": "20dd0741fca1009e5f641cd0fd1f319459ceeed0",
      "who": "saff@new-host-3.home",
      "when": "2009-06-04T00:09:23-04:00",
      "all": 262,
      "test": 117,
      "testable": 207,
      "pct": 56.5
    }
  ],
  "description": "JUnit 4 (master branch)",
  "baseURL": "https://github.com/junit-team/junit4/commit/"
}