{
  "commits": [
    {
      "id": "f45bfc614ca75b7d2f9141743c66817d0bc7eaff",
      "who": "steverstrong@users.sourceforge.net",
      "when": "2010-02-26T20:47:09+00:00",
      "all": 1634,
      "test": 123,
      "testable": 1600,
      "pct": 7.7
    },
    {
      "id": "754a986bd9e258474ce9bc0d42e92b126f60622c",
      "who": "flukefan@googlemail.com",
      "when": "2010-02-24T21:23:13+00:00",
      "all": 22,
      "test": 22,
      "testable": 22,
      "pct": 100.0
    },
    {
      "id": "bad53dfeb6f60e0bc5d4974ca9b6bdbda33a51a2",
      "who": "steverstrong@users.sourceforge.net",
      "when": "2010-02-24T16:45:34+00:00",
      "all": 22,
      "test": 22,
      "testable": 22,
      "pct": 100.0
    },
    {
      "id": "e41ff2c6deb3ef40aa69f0031beeb069d1b6fac0",
      "who": "steverstrong@users.sourceforge.net",
      "when": "2010-02-24T15:52:13+00:00",
      "all": 2142,
      "test": 400,
      "testable": 2098,
      "pct": 19.1
    },
    {
      "id": "7cc96b15668b2ee7ba9a43919ff936585814135d",
      "who": "flukefan@googlemail.com",
      "when": "2010-02-16T22:50:19+00:00",
      "all": 707,
      "test": 116,
      "testable": 673,
      "pct": 17.2
    },
    {
      "id": "0a132c589f6bac4353c566517c12b5acda4548bb",
      "who": "flukefan@googlemail.com",
      "when": "2010-02-07T12:15:51+00:00",
      "all": 236,
      "test": 36,
      "testable": 236,
      "pct": 15.3
    },
    {
      "id": "88d1edb9eb0fee9c039f98a544ede0c59eac4ba2",
      "who": "ayende@ayende.com",
      "when": "2010-02-01T20:48:56+00:00",
      "all": 39,
      "test": 0,
      "testable": 39,
      "pct": 0.0
    }
  ],
  "description": "NHibernate (master branch)",
  "baseURL": "https://github.com/nhibernate/nhibernate-core/commit/"
}