{
  "commits": [
    {
      "id": "5f7f3b17dfe2fbeecf82d5745c497b3ea94bf50a",
      "who": "Christopher Currie",
      "when": "2011-08-30T15:09:56-07:00",
      "all": 5,
      "test": 0,
      "testable": 5,
      "pct": 0.0
    },
    {
      "id": "ccf464189b116ea4ee458c2ccb24d64f9272e25b",
      "who": "Armin Ronacher",
      "when": "2011-08-30T14:36:50+02:00",
      "all": 80,
      "test": 23,
      "testable": 59,
      "pct": 39.0
    }
  ],
  "description": "Flask (master branch)",
  "baseURL": "https://github.com/spallets/flask/commit/"
}