{
  "commits": [
    {
      "id": "e304688f14e9f73d7984bdb148f45f6f7ecc337b",
      "who": "alex.yursha@icloud.com",
      "when": "2014-05-30T13:23:57+03:00",
      "all": 99,
      "test": 0,
      "testable": 99,
      "pct": 0.0
    },
    {
      "id": "df00d5eced3a7737b88de0f6f9e3673f0cf88f88",
      "who": "alex.yursha@icloud.com",
      "when": "2014-05-26T18:02:49+03:00",
      "all": 1121,
      "test": 0,
      "testable": 1117,
      "pct": 0.0
    },
    {
      "id": "23c8e97eef2bf6302b165bd04d642f8f7c961d26",
      "who": "kcooney+github@gmail.com",
      "when": "2014-05-29T08:31:20-07:00",
      "all": 137,
      "test": 0,
      "testable": 137,
      "pct": 0.0
    },
    {
      "id": "70f082f4d679cbf0b544758bc44321ecd168552d",
      "who": "kcooney+github@gmail.com",
      "when": "2014-05-27T07:46:27-07:00",
      "all": 26,
      "test": 0,
      "testable": 26,
      "pct": 0.0
    },
    {
      "id": "23c1ef4d6a436408080e9145415f792a158e9274",
      "who": "alex.yursha@icloud.com",
      "when": "2014-05-26T16:57:37+03:00",
      "all": 26,
      "test": 0,
      "testable": 26,
      "pct": 0.0
    },
    {
      "id": "a5d194fcb57b1b320ae808bc5a8d153f98f18a84",
      "who": "alex.yursha@icloud.com",
      "when": "2014-05-26T16:26:15+03:00",
      "all": 137,
      "test": 0,
      "testable": 137,
      "pct": 0.0
    },
    {
      "id": "8f59230f8be208e876a66cccd87f1a2d81aeccd3",
      "who": "eamonn@mcmanus.net",
      "when": "2014-05-22T10:27:22-07:00",
      "all": 8,
      "test": 0,
      "testable": 8,
      "pct": 0.0
    },
    {
      "id": "950702c6adbbcbbee0ce2061d674bf05e0c997b1",
      "who": "kcooney+github@gmail.com",
      "when": "2014-05-14T15:15:10-07:00",
      "all": 112,
      "test": 109,
      "testable": 112,
      "pct": 97.3
    },
    {
      "id": "5d05993602fc1e0ef384f3193790053ea706d0cd",
      "who": "charlie@yandex-team.ru",
      "when": "2014-05-03T21:09:47+04:00",
      "all": 112,
      "test": 109,
      "testable": 112,
      "pct": 97.3
    },
    {
      "id": "ad09a5cf24eaea5d09e43cfef84164bebb5fbc00",
      "who": "kcooney+github@gmail.com",
      "when": "2014-05-13T23:07:49-07:00",
      "all": 30,
      "test": 0,
      "testable": 30,
      "pct": 0.0
    },
    {
      "id": "fe410297b12268e4d287a34be4856172ce8a6c94",
      "who": "manan.shah.777@gmail.com",
      "when": "2014-05-13T22:39:44-07:00",
      "all": 30,
      "test": 0,
      "testable": 30,
      "pct": 0.0
    },
    {
      "id": "5e692e435599d43745be27da4013cefbc25bc2de",
      "who": "mail@marcphilipp.de",
      "when": "2014-05-12T21:12:17+02:00",
      "all": 151,
      "test": 10,
      "testable": 118,
      "pct": 8.5
    },
    {
      "id": "ae497d3811bfde738cbb2093aedc7c893bb67da6",
      "who": "mail@stefan-birkner.de",
      "when": "2014-05-12T13:47:03+02:00",
      "all": 9,
      "test": 9,
      "testable": 9,
      "pct": 100.0
    },
    {
      "id": "cfe6afadc81b72449c8b0cb96d51aa57f7a593b7",
      "who": "mengyanan@xiaomi.com",
      "when": "2014-05-12T16:26:11+08:00",
      "all": 9,
      "test": 9,
      "testable": 9,
      "pct": 100.0
    },
    {
      "id": "02ec1db120714910dbcb7eba1e55595f3904145c",
      "who": "mail@stefan-birkner.de",
      "when": "2014-05-05T09:40:50+02:00",
      "all": 121,
      "test": 118,
      "testable": 121,
      "pct": 97.5
    },
    {
      "id": "5784c8ab4042079a2df939fc5473cbebde697912",
      "who": "mail@stefan-birkner.de",
      "when": "2014-05-03T14:01:49+02:00",
      "all": 8,
      "test": 5,
      "testable": 8,
      "pct": 62.5
    },
    {
      "id": "56a03468f394f23a95f3a0cd2e80f2671963941d",
      "who": "ancosen@gmail.com",
      "when": "2014-05-03T09:17:38+02:00",
      "all": 8,
      "test": 5,
      "testable": 8,
      "pct": 62.5
    }
  ],
  "description": "JUnit 4 (master branch)",
  "baseURL": "https://github.com/junit-team/junit4/commit/"
}