{
  "commits": [
    {
      "id": "e21e0ba3dcd67d9048ecea9be5398b2a791e7bc5",
      "who": "antirez@gmail.com",
      "when": "2014-06-23T14:04:09+02:00",
      "all": 22,
      "test": 22,
      "testable": 22,
      "pct": 100.0
    },
    {
      "id": "e3bae84606389dadaff03c495d4ec37c306af3a1",
      "who": "antirez@gmail.com",
      "when": "2014-06-23T12:07:41+02:00",
      "all": 43,
      "test": 0,
      "testable": 43,
      "pct": 0.0
    },
    {
      "id": "be8f4d49d4015260e1fd14506dbf17ee3797cc78",
      "who": "antirez@gmail.com",
      "when": "2014-06-23T11:50:24+02:00",
      "all": 18,
      "test": 0,
      "testable": 18,
      "pct": 0.0
    },
    {
      "id": "5c7286efbde3ac2a584aa6cc8b0617c74a1adce0",
      "who": "antirez@gmail.com",
      "when": "2014-06-23T11:42:47+02:00",
      "all": 608,
      "test": 0,
      "testable": 608,
      "pct": 0.0
    },
    {
      "id": "1506c64c8b8b4a964f331f502a5d0006dd3077f0",
      "who": "antirez@gmail.com",
      "when": "2014-06-23T11:43:37+02:00",
      "all": 15,
      "test": 0,
      "testable": 15,
      "pct": 0.0
    },
    {
      "id": "af7647b20d42f0544944ca83492d5353617bb2b8",
      "who": "antirez@gmail.com",
      "when": "2014-06-23T10:07:13+02:00",
      "all": 14,
      "test": 0,
      "testable": 14,
      "pct": 0.0
    },
    {
      "id": "1206bdf13f3afbc242a52ee1ce190ef48432fa90",
      "who": "antirez@gmail.com",
      "when": "2014-06-23T09:08:51+02:00",
      "all": 24,
      "test": 24,
      "testable": 24,
      "pct": 100.0
    }
  ],
  "description": "Redis (unstable branch)",
  "baseURL": "https://github.com/antirez/redis/commit/"
}